otdf_python/__init__.py
otdf_python/__main__.py
otdf_python/address_normalizer.py
otdf_python/aesgcm.py
otdf_python/assertion_config.py
otdf_python/asym_crypto.py
otdf_python/auth_headers.py
otdf_python/autoconfigure_utils.py
otdf_python/cli.py
otdf_python/collection_store.py
otdf_python/collection_store_impl.py
otdf_python/config.py
otdf_python/connect_client.py
otdf_python/constants.py
otdf_python/crypto_utils.py
otdf_python/dpop.py
otdf_python/ecc_constants.py
otdf_python/ecc_mode.py
otdf_python/ecdh.py
otdf_python/eckeypair.py
otdf_python/header.py
otdf_python/invalid_zip_exception.py
otdf_python/kas_client.py
otdf_python/kas_connect_rpc_client.py
otdf_python/kas_info.py
otdf_python/kas_key_cache.py
otdf_python/key_type.py
otdf_python/key_type_constants.py
otdf_python/manifest.py
otdf_python/nanotdf.py
otdf_python/nanotdf_ecdsa_struct.py
otdf_python/nanotdf_type.py
otdf_python/policy_binding_serializer.py
otdf_python/policy_info.py
otdf_python/policy_object.py
otdf_python/policy_stub.py
otdf_python/resource_locator.py
otdf_python/sdk.py
otdf_python/sdk_builder.py
otdf_python/sdk_exceptions.py
otdf_python/symmetric_and_payload_config.py
otdf_python/tdf.py
otdf_python/tdf_reader.py
otdf_python/tdf_writer.py
otdf_python/token_source.py
otdf_python/version.py
otdf_python/zip_reader.py
otdf_python/zip_writer.py
otdf_python_proto/__init__.py
otdf_python_proto/authorization/__init__.py
otdf_python_proto/authorization/authorization_connect.py
otdf_python_proto/authorization/authorization_pb2.py
otdf_python_proto/authorization/authorization_pb2.pyi
otdf_python_proto/authorization/v2/authorization_connect.py
otdf_python_proto/authorization/v2/authorization_pb2.py
otdf_python_proto/authorization/v2/authorization_pb2.pyi
otdf_python_proto/common/__init__.py
otdf_python_proto/common/common_pb2.py
otdf_python_proto/common/common_pb2.pyi
otdf_python_proto/entity/__init__.py
otdf_python_proto/entity/entity_pb2.py
otdf_python_proto/entity/entity_pb2.pyi
otdf_python-0.4.2.dist-info/METADATA
otdf_python-0.4.2.dist-info/WHEEL
otdf_python-0.4.2.dist-info/licenses/LICENSE
otdf_python-0.4.2.dist-info/RECORD
