Metadata-Version: 2.4
Name: otdf-python
Version: 0.4.2
Summary: Unofficial OpenTDF SDK for Python
Project-URL: Homepage, https://github.com/b-long/opentdf-python-sdk
Project-URL: Repository, https://github.com/b-long/opentdf-python-sdk
Project-URL: Issues, https://github.com/b-long/opentdf-python-sdk/issues
Author-email: b-long <b-long@users.noreply.github.com>
License-File: LICENSE
Classifier: Development Status :: 4 - Beta
Classifier: Intended Audience :: Developers
Classifier: License :: OSI Approved :: MIT License
Classifier: Operating System :: OS Independent
Classifier: Programming Language :: Python :: 3
Classifier: Programming Language :: Python :: 3 :: Only
Classifier: Programming Language :: Python :: 3.10
Classifier: Programming Language :: Python :: 3.11
Classifier: Programming Language :: Python :: 3.12
Classifier: Programming Language :: Python :: 3.13
Classifier: Programming Language :: Python :: 3.14
Classifier: Topic :: Security :: Cryptography
Classifier: Topic :: Software Development :: Libraries :: Python Modules
Classifier: Typing :: Typed
Requires-Python: >=3.10
Requires-Dist: connect-python<0.7,>=0.6.0
Requires-Dist: cryptography>=45.0.4
Requires-Dist: grpcio-status>=1.74.0
Requires-Dist: grpcio-tools>=1.74.0
Requires-Dist: grpcio>=1.74.0
Requires-Dist: httpx>=0.28.1
Requires-Dist: protobuf>=6.31.1
Requires-Dist: protoc-gen-connect-python<0.7,>=0.6.0
Requires-Dist: protoc-gen-openapiv2>=0.0.1
Requires-Dist: pyjwt>=2.10.1
Requires-Dist: typing-extensions>=4.14.1
